{
  "openapi": "3.1.1",
  "info": {
    "title": "DevInbox.ApiService | v1",
    "version": "1.0.0"
  },
  "servers": [
    {
      "url": "http://localhost:5062/"
    }
  ],
  "paths": {
    "/mailboxes": {
      "post": {
        "tags": [
          "Mailboxes"
        ],
        "summary": "Create a new mailbox",
        "description": "Creates a new mailbox for receiving test emails. Can be temporary or persistent.",
        "operationId": "CreateMailbox",
        "requestBody": {
          "content": {
            "application/json": {
              "schema": {
                "$ref": "#/components/schemas/MailboxCreateModel"
              }
            }
          },
          "required": true
        },
        "responses": {
          "200": {
            "description": "OK",
            "content": {
              "application/json": {
                "schema": {
                  "$ref": "#/components/schemas/MailboxViewModel"
                }
              }
            }
          },
          "400": {
            "description": "Bad Request",
            "content": {
              "application/problem+json": {
                "schema": {
                  "$ref": "#/components/schemas/ProblemDetails"
                }
              }
            }
          }
        }
      }
    },
    "/messages/{key}/count": {
      "get": {
        "tags": [
          "Messages"
        ],
        "summary": "Get message count for a mailbox",
        "description": "Returns the total number of messages in the specified mailbox.",
        "operationId": "GetMessageCount",
        "parameters": [
          {
            "name": "key",
            "in": "path",
            "required": true,
            "schema": {
              "type": "string"
            }
          }
        ],
        "responses": {
          "200": {
            "description": "OK",
            "content": {
              "application/json": {
                "schema": {
                  "$ref": "#/components/schemas/MessageCountResult"
                }
              }
            }
          },
          "400": {
            "description": "Bad Request",
            "content": {
              "application/problem+json": {
                "schema": {
                  "$ref": "#/components/schemas/ProblemDetails"
                }
              }
            }
          },
          "403": {
            "description": "Forbidden",
            "content": {
              "application/problem+json": {
                "schema": {
                  "$ref": "#/components/schemas/ProblemDetails"
                }
              }
            }
          },
          "404": {
            "description": "Not Found",
            "content": {
              "application/problem+json": {
                "schema": {
                  "$ref": "#/components/schemas/ProblemDetails"
                }
              }
            }
          }
        }
      }
    },
    "/messages/{key}": {
      "get": {
        "tags": [
          "Messages"
        ],
        "summary": "Get messages from a mailbox",
        "description": "Retrieves messages from the specified mailbox with optional pagination. Default: skip=0, take=10, max take=25.",
        "operationId": "GetMessages",
        "parameters": [
          {
            "name": "key",
            "in": "path",
            "required": true,
            "schema": {
              "type": "string"
            }
          },
          {
            "name": "skip",
            "in": "query",
            "schema": {
              "pattern": "^-?(?:0|[1-9]\\d*)$",
              "type": [
                "integer",
                "string"
              ],
              "format": "int32"
            }
          },
          {
            "name": "take",
            "in": "query",
            "schema": {
              "pattern": "^-?(?:0|[1-9]\\d*)$",
              "type": [
                "integer",
                "string"
              ],
              "format": "int32"
            }
          }
        ],
        "responses": {
          "200": {
            "description": "OK",
            "content": {
              "application/json": {
                "schema": {
                  "$ref": "#/components/schemas/MessagesViewModel"
                }
              }
            }
          },
          "400": {
            "description": "Bad Request",
            "content": {
              "application/problem+json": {
                "schema": {
                  "$ref": "#/components/schemas/ProblemDetails"
                }
              }
            }
          },
          "403": {
            "description": "Forbidden",
            "content": {
              "application/problem+json": {
                "schema": {
                  "$ref": "#/components/schemas/ProblemDetails"
                }
              }
            }
          },
          "404": {
            "description": "Not Found",
            "content": {
              "application/problem+json": {
                "schema": {
                  "$ref": "#/components/schemas/ProblemDetails"
                }
              }
            }
          }
        }
      }
    },
    "/messages/{key}/single": {
      "get": {
        "tags": [
          "Messages"
        ],
        "summary": "Get single message from a mailbox",
        "description": "Retrieves a single message from the specified mailbox. Returns an error if the mailbox contains 0 or more than 1 message.",
        "operationId": "GetSingleMessage",
        "parameters": [
          {
            "name": "key",
            "in": "path",
            "required": true,
            "schema": {
              "type": "string"
            }
          }
        ],
        "responses": {
          "200": {
            "description": "OK",
            "content": {
              "application/json": {
                "schema": {
                  "$ref": "#/components/schemas/MessageViewModel"
                }
              }
            }
          },
          "400": {
            "description": "Bad Request",
            "content": {
              "application/problem+json": {
                "schema": {
                  "$ref": "#/components/schemas/ProblemDetails"
                }
              }
            }
          },
          "403": {
            "description": "Forbidden",
            "content": {
              "application/problem+json": {
                "schema": {
                  "$ref": "#/components/schemas/ProblemDetails"
                }
              }
            }
          },
          "404": {
            "description": "Not Found",
            "content": {
              "application/problem+json": {
                "schema": {
                  "$ref": "#/components/schemas/ProblemDetails"
                }
              }
            }
          }
        }
      }
    },
    "/messages/{key}/{template}/single": {
      "get": {
        "tags": [
          "Messages"
        ],
        "summary": "Get single message with template parsing",
        "description": "Retrieves a single message from the specified mailbox and parses it using the provided template. Returns an error if the mailbox contains 0 or more than 1 message.",
        "operationId": "GetSingleMessageWithTemplate",
        "parameters": [
          {
            "name": "key",
            "in": "path",
            "required": true,
            "schema": {
              "type": "string"
            }
          },
          {
            "name": "template",
            "in": "path",
            "required": true,
            "schema": {
              "type": "string"
            }
          }
        ],
        "responses": {
          "200": {
            "description": "OK",
            "content": {
              "application/json": {
                "schema": {
                  "$ref": "#/components/schemas/MessageParsedViewModel"
                }
              }
            }
          },
          "400": {
            "description": "Bad Request",
            "content": {
              "application/problem+json": {
                "schema": {
                  "$ref": "#/components/schemas/ProblemDetails"
                }
              }
            }
          },
          "403": {
            "description": "Forbidden",
            "content": {
              "application/problem+json": {
                "schema": {
                  "$ref": "#/components/schemas/ProblemDetails"
                }
              }
            }
          },
          "404": {
            "description": "Not Found",
            "content": {
              "application/problem+json": {
                "schema": {
                  "$ref": "#/components/schemas/ProblemDetails"
                }
              }
            }
          }
        }
      }
    },
    "/messages/{key}/last": {
      "get": {
        "tags": [
          "Messages"
        ],
        "summary": "Get the last message from a mailbox",
        "description": "Retrieves the most recent message from the specified mailbox. Returns an error if the mailbox is empty.",
        "operationId": "GetLastMessage",
        "parameters": [
          {
            "name": "key",
            "in": "path",
            "required": true,
            "schema": {
              "type": "string"
            }
          }
        ],
        "responses": {
          "200": {
            "description": "OK",
            "content": {
              "application/json": {
                "schema": {
                  "$ref": "#/components/schemas/MessageViewModel"
                }
              }
            }
          },
          "400": {
            "description": "Bad Request",
            "content": {
              "application/problem+json": {
                "schema": {
                  "$ref": "#/components/schemas/ProblemDetails"
                }
              }
            }
          },
          "403": {
            "description": "Forbidden",
            "content": {
              "application/problem+json": {
                "schema": {
                  "$ref": "#/components/schemas/ProblemDetails"
                }
              }
            }
          },
          "404": {
            "description": "Not Found",
            "content": {
              "application/problem+json": {
                "schema": {
                  "$ref": "#/components/schemas/ProblemDetails"
                }
              }
            }
          }
        }
      }
    },
    "/messages/{key}/{template}/last": {
      "get": {
        "tags": [
          "Messages"
        ],
        "summary": "Get the last message with template parsing",
        "description": "Retrieves the most recent message from the specified mailbox and parses it using the provided template. Returns an error if the mailbox is empty.",
        "operationId": "GetLastMessageWithTemplate",
        "parameters": [
          {
            "name": "key",
            "in": "path",
            "required": true,
            "schema": {
              "type": "string"
            }
          },
          {
            "name": "template",
            "in": "path",
            "required": true,
            "schema": {
              "type": "string"
            }
          }
        ],
        "responses": {
          "200": {
            "description": "OK",
            "content": {
              "application/json": {
                "schema": {
                  "$ref": "#/components/schemas/MessageParsedViewModel"
                }
              }
            }
          },
          "400": {
            "description": "Bad Request",
            "content": {
              "application/problem+json": {
                "schema": {
                  "$ref": "#/components/schemas/ProblemDetails"
                }
              }
            }
          },
          "403": {
            "description": "Forbidden",
            "content": {
              "application/problem+json": {
                "schema": {
                  "$ref": "#/components/schemas/ProblemDetails"
                }
              }
            }
          },
          "404": {
            "description": "Not Found",
            "content": {
              "application/problem+json": {
                "schema": {
                  "$ref": "#/components/schemas/ProblemDetails"
                }
              }
            }
          }
        }
      }
    },
    "/messages/{key}/get": {
      "get": {
        "tags": [
          "Messages"
        ],
        "summary": "Get a specific message by ID",
        "description": "Retrieves a specific message from the specified mailbox using its unique ID.",
        "operationId": "GetMessageById",
        "parameters": [
          {
            "name": "key",
            "in": "path",
            "required": true,
            "schema": {
              "type": "string"
            }
          },
          {
            "name": "id",
            "in": "query",
            "required": true,
            "schema": {
              "type": "string",
              "format": "uuid"
            }
          }
        ],
        "responses": {
          "200": {
            "description": "OK",
            "content": {
              "application/json": {
                "schema": {
                  "$ref": "#/components/schemas/MessageViewModel"
                }
              }
            }
          },
          "400": {
            "description": "Bad Request",
            "content": {
              "application/problem+json": {
                "schema": {
                  "$ref": "#/components/schemas/ProblemDetails"
                }
              }
            }
          },
          "403": {
            "description": "Forbidden",
            "content": {
              "application/problem+json": {
                "schema": {
                  "$ref": "#/components/schemas/ProblemDetails"
                }
              }
            }
          },
          "404": {
            "description": "Not Found",
            "content": {
              "application/problem+json": {
                "schema": {
                  "$ref": "#/components/schemas/ProblemDetails"
                }
              }
            }
          }
        }
      }
    },
    "/status": {
      "get": {
        "tags": [
          "Status"
        ],
        "summary": "Get API service status",
        "description": "Returns OK if the API service is running and available.",
        "operationId": "GetStatus",
        "responses": {
          "200": {
            "description": "OK"
          }
        }
      }
    }
  },
  "components": {
    "schemas": {
      "MailboxCreateModel": {
        "type": "object",
        "properties": {
          "name": {
            "maxLength": 100,
            "type": [
              "null",
              "string"
            ],
            "description": "Optional name for the mailbox. If not provided, a temporary mailbox will be created."
          },
          "projectName": {
            "maxLength": 100,
            "type": [
              "null",
              "string"
            ],
            "description": "Name of the project to associate the mailbox with. If not provided, uses the default project."
          },
          "isTemporary": {
            "type": "boolean",
            "description": "Whether the mailbox should be temporary or persistent.",
            "default": true
          }
        }
      },
      "MailboxViewModel": {
        "required": [
          "key",
          "password"
        ],
        "type": "object",
        "properties": {
          "key": {
            "type": "string",
            "description": "Unique identifier for the mailbox (<key>@devinbox.io)"
          },
          "password": {
            "type": "string",
            "description": "Password for accessing the mailbox (SMTP)"
          }
        }
      },
      "MessageCountResult": {
        "required": [
          "key",
          "count"
        ],
        "type": "object",
        "properties": {
          "key": {
            "type": "string",
            "description": "Mailbox unique identifier"
          },
          "count": {
            "pattern": "^-?(?:0|[1-9]\\d*)$",
            "type": [
              "integer",
              "string"
            ],
            "description": "Number of messages in the mailbox",
            "format": "int32"
          }
        }
      },
      "MessageParsedViewModel": {
        "required": [
          "uniqueId",
          "from",
          "to",
          "cc",
          "bcc",
          "subject",
          "body",
          "isHtml",
          "received"
        ],
        "type": "object",
        "properties": {
          "uniqueId": {
            "type": "string",
            "description": "Unique identifier for the message",
            "format": "uuid"
          },
          "from": {
            "type": [
              "null",
              "array"
            ],
            "items": {
              "type": "string"
            },
            "description": "Array of sender email addresses"
          },
          "to": {
            "type": [
              "null",
              "array"
            ],
            "items": {
              "type": "string"
            },
            "description": "Array of recipient email addresses"
          },
          "cc": {
            "type": [
              "null",
              "array"
            ],
            "items": {
              "type": "string"
            },
            "description": "Array of CC email addresses"
          },
          "bcc": {
            "type": [
              "null",
              "array"
            ],
            "items": {
              "type": "string"
            },
            "description": "Array of BCC email addresses"
          },
          "subject": {
            "type": [
              "null",
              "object"
            ],
            "additionalProperties": {
              "type": "string"
            },
            "description": "Parsed subject template parameters"
          },
          "body": {
            "type": [
              "null",
              "object"
            ],
            "additionalProperties": {
              "type": "string"
            },
            "description": "Parsed body template parameters"
          },
          "isHtml": {
            "type": "boolean",
            "description": "Whether the email body is HTML format"
          },
          "received": {
            "type": "string",
            "description": "Timestamp when the message was received",
            "format": "date-time"
          }
        }
      },
      "MessagesViewModel": {
        "required": [
          "key",
          "count",
          "messages"
        ],
        "type": "object",
        "properties": {
          "key": {
            "type": "string",
            "description": "Mailbox unique identifier"
          },
          "count": {
            "pattern": "^-?(?:0|[1-9]\\d*)$",
            "type": [
              "integer",
              "string"
            ],
            "description": "Total number of messages in the mailbox",
            "format": "int32"
          },
          "messages": {
            "type": "array",
            "items": {
              "$ref": "#/components/schemas/MessageViewModel"
            },
            "description": "Collection of message view models"
          }
        }
      },
      "MessageViewModel": {
        "required": [
          "uniqueId",
          "from",
          "to",
          "cc",
          "bcc",
          "subject",
          "body",
          "isHtml",
          "received"
        ],
        "type": "object",
        "properties": {
          "uniqueId": {
            "type": "string",
            "description": "Unique identifier for the message",
            "format": "uuid"
          },
          "from": {
            "type": [
              "null",
              "array"
            ],
            "items": {
              "type": "string"
            },
            "description": "Array of sender email addresses"
          },
          "to": {
            "type": [
              "null",
              "array"
            ],
            "items": {
              "type": "string"
            },
            "description": "Array of recipient email addresses"
          },
          "cc": {
            "type": [
              "null",
              "array"
            ],
            "items": {
              "type": "string"
            },
            "description": "Array of CC email addresses"
          },
          "bcc": {
            "type": [
              "null",
              "array"
            ],
            "items": {
              "type": "string"
            },
            "description": "Array of BCC email addresses"
          },
          "subject": {
            "type": [
              "null",
              "string"
            ],
            "description": "Email subject line"
          },
          "body": {
            "type": [
              "null",
              "string"
            ],
            "description": "Email body content"
          },
          "isHtml": {
            "type": "boolean",
            "description": "Whether the email body is HTML format"
          },
          "received": {
            "type": "string",
            "description": "Timestamp when the message was received",
            "format": "date-time"
          }
        }
      },
      "ProblemDetails": {
        "type": "object",
        "properties": {
          "type": {
            "type": [
              "null",
              "string"
            ]
          },
          "title": {
            "type": [
              "null",
              "string"
            ]
          },
          "status": {
            "pattern": "^-?(?:0|[1-9]\\d*)$",
            "type": [
              "null",
              "integer",
              "string"
            ],
            "format": "int32"
          },
          "detail": {
            "type": [
              "null",
              "string"
            ]
          },
          "instance": {
            "type": [
              "null",
              "string"
            ]
          }
        }
      }
    }
  },
  "tags": [
    {
      "name": "Mailboxes"
    },
    {
      "name": "Messages"
    },
    {
      "name": "Status"
    }
  ]
}